chat_pdf/__init__.py
chat_pdf/core.py
chat_pdf_qa-1.0.0.dist-info/METADATA
chat_pdf_qa-1.0.0.dist-info/WHEEL
chat_pdf_qa-1.0.0.dist-info/top_level.txt
chat_pdf_qa-1.0.0.dist-info/RECORD
