Metadata-Version: 2.4
Name: chat-pdf-qa
Version: 1.0.0
Summary: Chat with PDFs using LangChain In Few Lines of Code
Author: Adnan Syed
Project-URL: Homepage, https://github.com/Adnan-Tech-AI/chat-pdf
Requires-Python: >=3.10
Requires-Dist: langchain==1.2.0
Requires-Dist: langchain-classic==1.0.0
Requires-Dist: langchain-core==1.2.5
Requires-Dist: langchain-community==0.4.1
Requires-Dist: langchain-openai==1.1.6
Requires-Dist: langchain-text-splitters==1.1.0
Requires-Dist: langchain-chroma==1.1.0
Requires-Dist: chromadb==1.4.0
Requires-Dist: openai==2.14.0
Requires-Dist: pypdf>=4.0.0
